net_kusto_client/__init__.py
net_kusto_client/example.csv
net_kusto_client/local.settings.json
net_kusto_client-0.1.2.dist-info/licenses/LICENSE
net_kusto_client-0.1.2.dist-info/METADATA
net_kusto_client-0.1.2.dist-info/WHEEL
net_kusto_client-0.1.2.dist-info/top_level.txt
net_kusto_client-0.1.2.dist-info/RECORD
