Metadata-Version: 2.4
Name: net_kusto_client
Version: 0.1.2
Summary: A Kusto client package
Author-email: Larry Zhu <larry.lan.zhu@gmail.com>
License-Expression: MIT
Project-URL: Repository, https://github.com/myusernamehasbeentaken/net-kusto-client
Keywords: network,kusto,client
Classifier: Programming Language :: Python :: 3.9
Classifier: Operating System :: OS Independent
Requires-Python: >=3.9
License-File: LICENSE
Requires-Dist: azure-kusto-data>=5.0.3
Requires-Dist: azure-kusto-ingest>=5.0.3
Requires-Dist: pandas>=2.3.0
Requires-Dist: aiohttp>=3.12.13
Dynamic: license-file
